mit_scheme_kernel/__init__.py
mit_scheme_kernel/__main__.py
mit_scheme_kernel/config.yaml
mit_scheme_kernel/ex.ipynb
mit_scheme_kernel/kernel.py
mit_scheme_kernel/repl.py
mit_scheme_kernel/.ipynb_checkpoints/ex-checkpoint.ipynb
mit_scheme_kernel/magics/__init__.py
mit_scheme_kernel/magics/show_expression.py
mit_scheme_kernel-0.1.5.dist-info/METADATA
mit_scheme_kernel-0.1.5.dist-info/WHEEL
mit_scheme_kernel-0.1.5.dist-info/RECORD
