Metadata-Version: 2.4
Name: mit-scheme-kernel
Version: 0.1.5
Summary: A MIT/GNU Scheme Jupyter kernel based on metakernel
Project-URL: Homepage, https://github.com/twaclaw/mit-scheme-kernel
Project-URL: Documentation, https://github.com/twaclaw/mit-scheme-kernel
Project-URL: Issues, https://github.com/twaclaw/mit-scheme-kernel/issues
Author-email: Diego Sandoval <dsandovalv@gmail.com>
Maintainer-email: Diego Sandoval <dsandovalv@gmail.com>
Keywords: jupyter,mechanics,metakernel,mit-scheme,mit-scheme-kernel,scheme,scmutils
Classifier: Development Status :: 4 - Beta
Classifier: Intended Audience :: Developers
Classifier: Intended Audience :: Education
Classifier: Intended Audience :: Science/Research
Classifier: License :: OSI Approved :: MIT License
Classifier: Operating System :: POSIX
Classifier: Operating System :: Unix
Classifier: Programming Language :: Python
Classifier: Programming Language :: Python :: 3
Classifier: Programming Language :: Python :: 3.10
Classifier: Programming Language :: Python :: 3.11
Classifier: Programming Language :: Python :: 3.12
Classifier: Programming Language :: Python :: 3.13
Classifier: Programming Language :: Python :: 3.14
Classifier: Topic :: Scientific/Engineering
Requires-Python: >=3.10
Requires-Dist: metakernel>=0.30.3
Requires-Dist: pyyaml>=6.0.2
Provides-Extra: dev
Requires-Dist: hatch; extra == 'dev'
Requires-Dist: pre-commit; extra == 'dev'
Requires-Dist: ruff; extra == 'dev'
